{"$schema":"","version":"1.0.0","description":"Configuración para Prepare-FullEnv: servicios Docker, API y clientes a levantar.","dockerComposePath":"docker-compose.yml","mysqlContainerName":"GesFer_product_db","dockerServices":["gesfer-db","cache","adminer"],"startApi":{"enabled":true,"workingDir":"src/Api","command":"dotnet run","serviceName":"ProductApi","healthUrl":"http://localhost:5020/health"},"startClients":[],"healthCheck":{"mysqlMaxAttempts":30,"mysqlRetrySeconds":2,"apiWaitSeconds":15}}
